vab/__init__.py
vab/address_book.py
vab/calculator.py
vab/files_sort.py
vab/main.py
vab/note_book.py
vab-1.0.2.dist-info/LICENSE
vab-1.0.2.dist-info/METADATA
vab-1.0.2.dist-info/WHEEL
vab-1.0.2.dist-info/entry_points.txt
vab-1.0.2.dist-info/top_level.txt
vab-1.0.2.dist-info/RECORD
