Metadata-Version: 2.1
Name: vab
Version: 1.0.2
Summary: very helpful assistant bot
Home-page: https://github.com/VadimTrubay/vab.git
Author: Trubay_Vadim
Author-email: vadnetvadnet@ukr.net
License: MIT
License-File: LICENSE
Requires-Dist: numexpr
Requires-Dist: colorama
